MANIFEST.in
README.md
setup.py
config/config.json
kings_selenium/__init__.py
kings_selenium/constants.py
kings_selenium/selenium_common.py
kings_selenium/selenium_phone.py
kings_selenium/selenium_web.py
kings_selenium.egg-info/PKG-INFO
kings_selenium.egg-info/SOURCES.txt
kings_selenium.egg-info/dependency_links.txt
kings_selenium.egg-info/requires.txt
kings_selenium.egg-info/top_level.txt
test/__init__.py
test/test_phone.py
test/test_web.py