Metadata-Version: 2.1
Name: kings-selenium
Version: 1.0.3
Summary: encapsulation the web and phone(appium) functions used by selenium 
Home-page: https://github.com/kings1990/kings_selenium
Author: kings
Author-email: 963987632@qq.com
License: MIT
Platform: UNKNOWN
Classifier: Programming Language :: Python :: 3
Classifier: License :: OSI Approved :: MIT License
Classifier: Operating System :: OS Independent
Requires-Python: >=3
